{
  "_comment": "Конфиг сериалов и фильмов. Ключ = часть имени файла (регистр не важен).",
  "аватар": {
    "title": "Аватар: Легенда об Аанге",
    "emoji": "⚡️",
    "hashtags": ["#аватар", "#аниме", "#мультфильм", "#тикток", "#avatar", "#аанг"]
  },
  "наруто": {
    "title": "Наруто",
    "emoji": "🍃",
    "hashtags": ["#наруто", "#аниме", "#naruto", "#тикток", "#мультфильм"]
  },
  "ванпис": {
    "title": "Ван Пис",
    "emoji": "☠️",
    "hashtags": ["#ванпис", "#аниме", "#onepiece", "#тикток", "#мультфильм"]
  },
  "атака": {
    "title": "Атака Титанов",
    "emoji": "⚔️",
    "hashtags": ["#атакататанов", "#аниме", "#attackontitan", "#тикток"]
  },
  "игра": {
    "title": "Игра Престолов",
    "emoji": "🐉",
    "hashtags": ["#играпрестолов", "#сериал", "#gameofthrones", "#тикток"]
  },
  "_default": {
    "title": null,
    "emoji": "🎬",
    "hashtags": ["#сериал", "#кино", "#тикток", "#фильм"]
  }
}
